shift15m/__init__.py
shift15m/constants.py
shift15m/datasets/__init__.py
shift15m/datasets/base_dataset.py
shift15m/datasets/df_manipulations.py
shift15m/datasets/download_tarfiles.py
shift15m/datasets/feature_tar_extractor.py
shift15m/datasets/helper.py
shift15m/datasets/imagefeature_torch.py
shift15m/datasets/numlikes_tabular.py
shift15m/datasets/outfitfeature.py
shift15m/datasets/set_dataloader.py
shift15m/datasets/sumprices_tabular.py
shift15m/msgs.py
shift15m-0.2.0.dist-info/LICENSE.MIT
shift15m-0.2.0.dist-info/LICENSE.CC
shift15m-0.2.0.dist-info/WHEEL
shift15m-0.2.0.dist-info/METADATA
shift15m-0.2.0.dist-info/RECORD
