Metadata-Version: 2.1
Name: shift15m
Version: 0.2.0
Summary: Large-scale multiobective dataset with dataset shift.
Author: ZOZO Research SHIFT15M Team
Requires-Python: >=3.7.1,<4.0
Classifier: Programming Language :: Python :: 3
Classifier: Programming Language :: Python :: 3.10
Classifier: Programming Language :: Python :: 3.8
Classifier: Programming Language :: Python :: 3.9
Requires-Dist: Sphinx (>=4.0.2,<5.0.0)
Requires-Dist: furo (>=2021.6.24-beta.37,<2022.0.0)
Requires-Dist: matplotlib (>=3.4.2,<4.0.0)
Requires-Dist: pandas (>=1.2.4,<2.0.0)
Requires-Dist: requests (>=2.26.0,<3.0.0)
Requires-Dist: seaborn (>=0.11.1,<0.12.0)
Requires-Dist: sklearn (>=0.0,<0.1)
Requires-Dist: tqdm (>=4.62.0,<5.0.0)
